Metadata-Version: 2.1
Name: odoo-addon-server_action_navigate
Version: 17.0.1.0.0.2
Requires-Python: >=3.10
Requires-Dist: odoo>=17.0a,<17.1dev
Summary: Navigate between any items of any Odoo Models
Home-page: https://github.com/OCA/server-backend
License: AGPL-3
Author: GRAP, Odoo Community Association (OCA)
Author-email: support@odoo-community.org
Classifier: Programming Language :: Python
Classifier: Framework :: Odoo
Classifier: Framework :: Odoo :: 17.0
Classifier: License :: OSI Approved :: GNU Affero General Public License v3
